AUTHORS
CHANGES.rst
LICENSE
MANIFEST.in
README.rst
setup.cfg
setup.py
docs/Makefile
docs/conf.py
docs/contributing.rst
docs/examples.rst
docs/index.rst
docs/installation.rst
docs/logging.rst
docs/make.bat
docs/management.rst
docs/operation.rst
docs/requirements.rst
docs/template.rst
docs/_theme/nature/theme.conf
docs/_theme/nature/static/nature.css_t
docs/_theme/nature/static/pygments.css
docs/reference/image.rst
docs/reference/index.rst
docs/reference/settings.rst
sorl/__init__.py
sorl/thumbnail/__init__.py
sorl/thumbnail/base.py
sorl/thumbnail/compat.py
sorl/thumbnail/default.py
sorl/thumbnail/fields.py
sorl/thumbnail/helpers.py
sorl/thumbnail/images.py
sorl/thumbnail/log.py
sorl/thumbnail/models.py
sorl/thumbnail/parsers.py
sorl/thumbnail/shortcuts.py
sorl/thumbnail/admin/__init__.py
sorl/thumbnail/admin/current.py
sorl/thumbnail/conf/__init__.py
sorl/thumbnail/conf/defaults.py
sorl/thumbnail/engines/__init__.py
sorl/thumbnail/engines/base.py
sorl/thumbnail/engines/convert_engine.py
sorl/thumbnail/engines/pgmagick_engine.py
sorl/thumbnail/engines/pil_engine.py
sorl/thumbnail/engines/vipsthumbnail_engine.py
sorl/thumbnail/engines/wand_engine.py
sorl/thumbnail/kvstores/__init__.py
sorl/thumbnail/kvstores/base.py
sorl/thumbnail/kvstores/cached_db_kvstore.py
sorl/thumbnail/kvstores/dbm_kvstore.py
sorl/thumbnail/kvstores/dynamodb_kvstore.py
sorl/thumbnail/kvstores/redis_kvstore.py
sorl/thumbnail/management/__init__.py
sorl/thumbnail/management/commands/__init__.py
sorl/thumbnail/management/commands/thumbnail.py
sorl/thumbnail/migrations/0001_initial.py
sorl/thumbnail/migrations/__init__.py
sorl/thumbnail/templatetags/__init__.py
sorl/thumbnail/templatetags/sorl_thumbnail.py
sorl/thumbnail/templatetags/thumbnail.py
sorl_thumbnail_jdmueller.egg-info/PKG-INFO
sorl_thumbnail_jdmueller.egg-info/SOURCES.txt
sorl_thumbnail_jdmueller.egg-info/dependency_links.txt
sorl_thumbnail_jdmueller.egg-info/not-zip-safe
sorl_thumbnail_jdmueller.egg-info/top_level.txt
tests/__init__.py
tests/data/1_topleft.jpg
tests/data/2_topright.jpg
tests/data/3_bottomright.jpg
tests/data/4_bottomleft.jpg
tests/data/5_lefttop.jpg
tests/data/6_righttop.jpg
tests/data/7_rightbottom.jpg
tests/data/8_leftbottom.jpg
