Metadata-Version: 1.2
Name: sorl-thumbnail-jdmueller
Version: 12.5.0
Summary: Thumbnails for Django
Home-page: https://github.com/jdmueller/sorl-thumbnail-jdmueller
Author: Jonathan Mueller
Author-email: jdmueller@protonmail.ch
Maintainer: jdmueller
Maintainer-email: jdmueller@protonmail.ch
License: BSD
Platform: any
Classifier: Development Status :: 2 - Pre-Alpha
Classifier: Environment :: Web Environment
Classifier: Intended Audience :: Developers
Classifier: License :: OSI Approved :: BSD License
Classifier: Operating System :: OS Independent
Classifier: Programming Language :: Python
Classifier: Programming Language :: Python :: 2.7
Classifier: Programming Language :: Python :: 3.4
Classifier: Programming Language :: Python :: 3.5
Classifier: Programming Language :: Python :: 3.6
Classifier: Programming Language :: Python :: 3.7
Classifier: Topic :: Internet :: WWW/HTTP :: Dynamic Content
Classifier: Topic :: Multimedia :: Graphics
Classifier: Framework :: Django
Classifier: Framework :: Django :: 1.11
Classifier: Framework :: Django :: 2.0
Classifier: Framework :: Django :: 2.1
Classifier: Framework :: Django :: 2.2
